mineru_vl_utils/__init__.py
mineru_vl_utils/mineru_client.py
mineru_vl_utils/structs.py
mineru_vl_utils/version.py
mineru_vl_utils/logits_processor/vllm_v0_no_repeat_ngram.py
mineru_vl_utils/logits_processor/vllm_v1_no_repeat_ngram.py
mineru_vl_utils/post_process/__init__.py
mineru_vl_utils/post_process/equation_big.py
mineru_vl_utils/post_process/equation_block.py
mineru_vl_utils/post_process/equation_double_subscript.py
mineru_vl_utils/post_process/equation_fix_eqqcolon.py
mineru_vl_utils/post_process/equation_left_right.py
mineru_vl_utils/post_process/equation_leq.py
mineru_vl_utils/post_process/equation_unbalanced_braces.py
mineru_vl_utils/post_process/otsl2html.py
mineru_vl_utils/vlm_client/__init__.py
mineru_vl_utils/vlm_client/base_client.py
mineru_vl_utils/vlm_client/http_client.py
mineru_vl_utils/vlm_client/lmdeploy_engine_client.py
mineru_vl_utils/vlm_client/mlx_client.py
mineru_vl_utils/vlm_client/transformers_client.py
mineru_vl_utils/vlm_client/utils.py
mineru_vl_utils/vlm_client/vllm_async_engine_client.py
mineru_vl_utils/vlm_client/vllm_engine_client.py
mineru_vl_utils-0.1.21.dist-info/licenses/LICENSE.md
mineru_vl_utils-0.1.21.dist-info/METADATA
mineru_vl_utils-0.1.21.dist-info/WHEEL
mineru_vl_utils-0.1.21.dist-info/top_level.txt
mineru_vl_utils-0.1.21.dist-info/RECORD
