Metadata-Version: 2.4
Name: mineru_vl_utils
Version: 0.1.21
Summary: Utilities for MinerU Vision-Language models
Author-email: Jin Zhen Jiang <jinzhenjiang@pjlab.org.cn>, Zhao Xiao Meng <zhaoxiaomeng@pjlab.org.cn>, Zhao Zhi Yuan <zhaozhiyuan@pjlab.org.cn>
License-Expression: AGPL-3.0
Project-URL: Homepage, https://github.com/opendatalab/mineru-vl-utils
Project-URL: Issues, https://github.com/opendatalab/mineru-vl-utils/issues
Classifier: Programming Language :: Python :: 3
Classifier: Operating System :: OS Independent
Requires-Python: <3.14,>=3.10
License-File: LICENSE.md
Requires-Dist: httpx
Requires-Dist: httpx-retries
Requires-Dist: aiofiles
Requires-Dist: pillow
Requires-Dist: pydantic
Requires-Dist: loguru
Provides-Extra: transformers
Requires-Dist: torch<3,>=2.6.0; extra == "transformers"
Requires-Dist: transformers<5.0.0,>=4.51.1; extra == "transformers"
Requires-Dist: accelerate>=1.5.1; extra == "transformers"
Requires-Dist: torchvision; extra == "transformers"
Provides-Extra: vllm
Requires-Dist: vllm<0.12,>=0.10.1.1; extra == "vllm"
Provides-Extra: mlx
Requires-Dist: mlx-vlm<0.4.0,>=0.3.3; extra == "mlx"
Provides-Extra: lmdeploy
Requires-Dist: lmdeploy<0.12,>=0.10.2; extra == "lmdeploy"
Requires-Dist: qwen_vl_utils; extra == "lmdeploy"
Dynamic: license-file
